prodiapy/__init__.py
prodiapy/_client.py
prodiapy/aio.py
prodiapy/exceptions.py
prodiapy/resources/__init__.py
prodiapy/resources/constants.py
prodiapy/resources/engine.py
prodiapy/resources/facerestore.py
prodiapy/resources/faceswap.py
prodiapy/resources/general.py
prodiapy/resources/logger.py
prodiapy/resources/photomaker.py
prodiapy/resources/response.py
prodiapy/resources/stablediffusion/__init__.py
prodiapy/resources/stablediffusion/sd15.py
prodiapy/resources/stablediffusion/sdxl.py
prodiapy/resources/stablediffusion/template.py
prodiapy/resources/upscale.py
prodiapy/resources/utils.py
prodiapy-5.1.6.dist-info/LICENSE
prodiapy-5.1.6.dist-info/METADATA
prodiapy-5.1.6.dist-info/WHEEL
prodiapy-5.1.6.dist-info/RECORD
