Metadata-Version: 2.1
Name: prodiapy
Version: 5.1.6
Summary: Package for using Prodia API
Author: zenafey
Author-email: zenafey@eugw.ru
Requires-Python: >=3.8,<4.0
Classifier: Programming Language :: Python :: 3
Classifier: Programming Language :: Python :: 3.8
Classifier: Programming Language :: Python :: 3.9
Classifier: Programming Language :: Python :: 3.10
Classifier: Programming Language :: Python :: 3.11
Classifier: Programming Language :: Python :: 3.12
Requires-Dist: aiohttp (>=3.9.1,<4.0.0)
Requires-Dist: requests (>=2.31.0,<3.0.0)
Requires-Dist: zenlogger (>=0.0.2,<0.0.3)
